<?xml version="1.0" encoding="UTF-8"?>
<NFSe xmlns="http://www.sped.fazenda.gov.br/nfse" versao="1.00">
<infNFSe Id="NFS35060031210497112000153000000000018126020522652385">
<xLocEmi>BAURU</xLocEmi>
<xLocPrestacao>Bauru</xLocPrestacao>
<nNFSe>181</nNFSe>
<cLocIncid>3506003</cLocIncid>
<xLocIncid>Bauru</xLocIncid>
<xTribNac>Instrução, treinamento, orientação pedagógica e educacional, avaliação de conhecimentos de qualquer natureza.</xTribNac>
<verAplic>SilTecnologia_v1.00</verAplic>
<ambGer>1</ambGer>
<tpEmis>2</tpEmis>
<cStat>100</cStat>
<dhProc>2026-02-25T00:00:00-03:00</dhProc>
<nDFSe>52265238</nDFSe>
<emit>
<CNPJ>10497112000153</CNPJ>
<IM>508595</IM>
<xNome>CASA DO CIRCO PRODUCOES ARTISTICAS LTDA</xNome>
<enderNac>
<xLgr>17054-140 - RUA BOLÍVIA, 5-43</xLgr>
<nro>0</nro>
<xBairro>JARDIM TERRA BRANCA</xBairro>
<cMun>3506003</cMun>
<UF>SP</UF>
<CEP>17054140</CEP>
</enderNac>
<fone>1432264445</fone>
<email>FISCAL@JRASSESSORIA.COM.BR</email>
</emit>
<valores>
<vBC>1656.00</vBC>
<pAliqAplic>2.00</pAliqAplic>
<vISSQN>33.12</vISSQN>
<vTotalRet>33.12</vTotalRet>
<vLiq>1622.88</vLiq>
</valores>
<DPS versao="1.00">
<infDPS Id="DPS350600321049711200015349999000000000000181">
<tpAmb>1</tpAmb>
<dhEmi>2026-02-25T00:00:00-03:00</dhEmi>
<verAplic>SilTecnologia_v1.00</verAplic>
<serie>49999</serie>
<nDPS>181</nDPS>
<dCompet>2026-01-01</dCompet>
<tpEmit>1</tpEmit>
<cLocEmi>3506003</cLocEmi>
<prest>
<CNPJ>10497112000153</CNPJ>
<IM>508595</IM>
<fone>1432264445</fone>
<email>FISCAL@JRASSESSORIA.COM.BR</email>
<regTrib>
<opSimpNac>3</opSimpNac>
<regApTribSN/>
<regEspTrib>0</regEspTrib>
</regTrib>
</prest>
<toma>
<CNPJ>09204552000196</CNPJ>
<xNome>FOUR C EMPREENDIMENTO EDUCACIONAL LTDA.</xNome>
<end>
<endNac>
<cMun>3506003</cMun>
<CEP>17018520</CEP>
</endNac>
<xLgr>AVENIDA AFFONSO JOSE AIELLO 12-50</xLgr>
<nro>12-50</nro>
<xBairro>VILA AVIAÇÃO</xBairro>
</end>
</toma>
<serv>
<locPrest>
<cLocPrestacao>3506003</cLocPrestacao>
</locPrest>
<cServ>
<cTribNac>080201</cTribNac>
<xDescServ>AULAS DE CIRCO E TECIDO COMPETENCIA 01/2026</xDescServ>
<cNBS>122051100</cNBS>
</cServ>
</serv>
<valores>
<vServPrest>
<vServ>1656.00</vServ>
</vServPrest>
<trib>
<tribMun>
<tribISSQN>1</tribISSQN>
<tpRetISSQN>2</tpRetISSQN>
</tribMun>
<tribFed/>
<totTrib>
<vTotTrib>
<vTotTribFed>0.00</vTotTribFed>
<vTotTribEst>0.00</vTotTribEst>
<vTotTribMun>33.12</vTotTribMun>
</vTotTrib>
</totTrib>
</trib>
</valores>
</infDPS>
</DPS>
</infNFSe>
</NFSe>

