<?xml version="1.0" encoding="ISO-8859-1"?><ConsultarNfseResposta xmlns="http://www.abrasf.org.br/ABRASF/arquivos/nfse.xsd"><ListaNfse><CompNfse><Nfse><InfNfse id="18180"><Numero>18180</Numero><CodigoVerificacao>35060031229557269000155000000001818026020516718942</CodigoVerificacao><DataEmissao>2026-02-02T00:00:00</DataEmissao><IdentificacaoRps><Numero>18525</Numero><Serie>17</Serie><Tipo>1</Tipo><Status>1</Status></IdentificacaoRps><NaturezaOperacao>1</NaturezaOperacao><OptanteSimplesNacional>1</OptanteSimplesNacional><IncentivadorCultural>2</IncentivadorCultural><Competencia>2026-02-01T00:00:00</Competencia><Servico><Valores><ValorServicos>265.0</ValorServicos><ValorDeducoes>0</ValorDeducoes><ValorPis>0.0</ValorPis><ValorCofins>0.0</ValorCofins><ValorInss>0.0</ValorInss><ValorIr>0.0</ValorIr><ValorCsll>0.0</ValorCsll><ValorIss>5.3</ValorIss><OutrasRetencoes>0.0</OutrasRetencoes><BaseCalculo>265.0</BaseCalculo><Aliquota>2.0</Aliquota><ValorLiquidoNfse>259.7</ValorLiquidoNfse><DescontoCondicionado>0.0</DescontoCondicionado><DescontoIncondicionado>0.0</DescontoIncondicionado></Valores><IssRetido>1</IssRetido><ItemListaServico>040101</ItemListaServico><CodigoCnae/><Discriminacao>EXAMES</Discriminacao><CodigoMunicipio>3506003</CodigoMunicipio><ExigibilidadeISS>1</ExigibilidadeISS></Servico><PrestadorServico><IdentificacaoPrestador><Cnpj>29557269000155</Cnpj><InscricaoMunicipal>572578</InscricaoMunicipal></IdentificacaoPrestador><RazaoSocial>PREVENTIVA BAURU MEDICINA E SEGURANCA DO TRABALHO LTDA.</RazaoSocial><NomeFantasia/><Endereco><Endereco>TREZE DE MAIO, 16-30 - VILA NOEMY</Endereco><Numero>0001</Numero><Bairro>CEP 17014-450 - BAURU - SP</Bairro><CodigoMunicipio>3506003</CodigoMunicipio><Uf>SP</Uf><Cep>17014-450</Cep></Endereco><Contato><Telefone>(14) 3010-2539</Telefone></Contato></PrestadorServico><TomadorServico><IdentificacaoTomador><CpfCnpj><Cnpj>07962637000108</Cnpj></CpfCnpj></IdentificacaoTomador><RazaoSocial>EMPORIUM COMERCIO DE ACRILICOS LTDA</RazaoSocial><Endereco><Endereco>AV MANOEL DUQUE, 2-10</Endereco><Numero/><Bairro>NAO INFORMADO</Bairro><CodigoMunicipio>3506003</CodigoMunicipio><Uf>SP</Uf><Cep>17030110</Cep></Endereco><Contato><Email/></Contato></TomadorServico><OrgaoGerador><CodigoMunicipio>3506003</CodigoMunicipio><Uf>SP</Uf></OrgaoGerador></InfNfse></Nfse></CompNfse><CompNfse><Nfse><InfNfse id="64920"><Numero>64920</Numero><CodigoVerificacao>35060031211936539000173000000006492026020517033769</CodigoVerificacao><DataEmissao>2026-02-03T00:00:00</DataEmissao><IdentificacaoRps><Numero>37860</Numero><Serie>00001</Serie><Tipo>1</Tipo><Status>1</Status></IdentificacaoRps><NaturezaOperacao>1</NaturezaOperacao><OptanteSimplesNacional>2</OptanteSimplesNacional><IncentivadorCultural>2</IncentivadorCultural><Competencia>2026-02-01T00:00:00</Competencia><Servico><Valores><ValorServicos>930.12</ValorServicos><ValorDeducoes>0</ValorDeducoes><ValorPis>0.0</ValorPis><ValorCofins>0.0</ValorCofins><ValorInss>0.0</ValorInss><ValorIr>0.0</ValorIr><ValorCsll>0.0</ValorCsll><ValorIss>18.6</ValorIss><OutrasRetencoes>0.0</OutrasRetencoes><BaseCalculo>930.12</BaseCalculo><Aliquota>2.0</Aliquota><ValorLiquidoNfse>911.52</ValorLiquidoNfse><DescontoCondicionado>0.0</DescontoCondicionado><DescontoIncondicionado>0.0</DescontoIncondicionado></Valores><IssRetido>1</IssRetido><ItemListaServico>070101</ItemListaServico><CodigoCnae/><Discriminacao>SERVICO DE ENGENHARIA ELETRICA</Discriminacao><CodigoMunicipio>3506003</CodigoMunicipio><ExigibilidadeISS>1</ExigibilidadeISS></Servico><PrestadorServico><IdentificacaoPrestador><Cnpj>11936539000173</Cnpj><InscricaoMunicipal>514501</InscricaoMunicipal></IdentificacaoPrestador><RazaoSocial>ULTRAGAZ ENERGIA E CORRETAGEM DE SEGUROS LTDA</RazaoSocial><NomeFantasia/><Endereco><Endereco>ANTÔNIO ALVES, 35-48 - VILA AEROPORTO BAURU</Endereco><Numero>0001</Numero><Bairro>CEP 17012-431 - BAURU - SP</Bairro><CodigoMunicipio>3506003</CodigoMunicipio><Uf>SP</Uf><Cep>17012-431</Cep></Endereco><Contato><Telefone>(14) 3104-8200</Telefone></Contato></PrestadorServico><TomadorServico><IdentificacaoTomador><CpfCnpj><Cnpj>07962637000108</Cnpj></CpfCnpj></IdentificacaoTomador><RazaoSocial>EMPORIUM COMERCIO DE ACRILICOS LTDA</RazaoSocial><Endereco><Endereco>AVENIDA MANOEL DUQUE</Endereco><Numero/><Bairro>JARDIM GUADALAJARA</Bairro><CodigoMunicipio>3506003</CodigoMunicipio><Uf>SP</Uf><Cep>17030110</Cep></Endereco><Contato><Email/></Contato></TomadorServico><OrgaoGerador><CodigoMunicipio>3506003</CodigoMunicipio><Uf>SP</Uf></OrgaoGerador></InfNfse></Nfse></CompNfse><CompNfse><Nfse><InfNfse id="81605"><Numero>81605</Numero><CodigoVerificacao>35060031211349397000148000000008160526020517272883</CodigoVerificacao><DataEmissao>2026-02-04T00:00:00</DataEmissao><IdentificacaoRps><Numero>40042</Numero><Serie>1</Serie><Tipo>1</Tipo><Status>1</Status></IdentificacaoRps><NaturezaOperacao>1</NaturezaOperacao><OptanteSimplesNacional>1</OptanteSimplesNacional><IncentivadorCultural>2</IncentivadorCultural><Competencia>2026-02-01T00:00:00</Competencia><Servico><Valores><ValorServicos>130.0</ValorServicos><ValorDeducoes>0</ValorDeducoes><ValorPis>0.0</ValorPis><ValorCofins>0.0</ValorCofins><ValorInss>0.0</ValorInss><ValorIr>0.0</ValorIr><ValorCsll>0.0</ValorCsll><ValorIss>6.5</ValorIss><OutrasRetencoes>0.0</OutrasRetencoes><BaseCalculo>130.0</BaseCalculo><Aliquota>5.0</Aliquota><ValorLiquidoNfse>123.5</ValorLiquidoNfse><DescontoCondicionado>0.0</DescontoCondicionado><DescontoIncondicionado>0.0</DescontoIncondicionado></Valores><IssRetido>1</IssRetido><ItemListaServico>110201</ItemListaServico><CodigoCnae/><Discriminacao>SERVICO DE MONITORAMENTO DE ALARME 24H|||VALOR APROX. DE TRIBUTO (15,71%) |FONTE: IBPT|</Discriminacao><CodigoMunicipio>3506003</CodigoMunicipio><ExigibilidadeISS>1</ExigibilidadeISS></Servico><PrestadorServico><IdentificacaoPrestador><Cnpj>11349397000148</Cnpj><InscricaoMunicipal>512602</InscricaoMunicipal></IdentificacaoPrestador><RazaoSocial>VITIVER SISTEMAS DE SEGURANCA ELETRONICA LTDA</RazaoSocial><NomeFantasia/><Endereco><Endereco>RODRIGUES ALVES, 15-81 - VILA BONFIM</Endereco><Numero>0001</Numero><Bairro>CEP 17013-000 - BAURU - SP</Bairro><CodigoMunicipio>3506003</CodigoMunicipio><Uf>SP</Uf><Cep>17013-000</Cep></Endereco><Contato><Telefone>(14) 3206-1888</Telefone></Contato></PrestadorServico><TomadorServico><IdentificacaoTomador><CpfCnpj><Cnpj>07962637000108</Cnpj></CpfCnpj></IdentificacaoTomador><RazaoSocial>EMPORIUM COMERCIO DE ACRILICOS LTDA EPP</RazaoSocial><Endereco><Endereco>AVENIDA MANOEL DUQUE</Endereco><Numero/><Bairro>JARDIM GUADALAJARA</Bairro><CodigoMunicipio>3506003</CodigoMunicipio><Uf>SP</Uf><Cep>17030110</Cep></Endereco><Contato><Email>admin@emporiumacrilicos.com.br</Email></Contato></TomadorServico><OrgaoGerador><CodigoMunicipio>3506003</CodigoMunicipio><Uf>SP</Uf></OrgaoGerador></InfNfse></Nfse></CompNfse><CompNfse><Nfse><InfNfse id="7719"><Numero>7719</Numero><CodigoVerificacao>35060031229726322000102000000000771926020519857901</CodigoVerificacao><DataEmissao>2026-02-09T00:00:00</DataEmissao><IdentificacaoRps><Numero>7719</Numero><Serie>1</Serie><Tipo>1</Tipo><Status>1</Status></IdentificacaoRps><NaturezaOperacao>1</NaturezaOperacao><OptanteSimplesNacional>2</OptanteSimplesNacional><IncentivadorCultural>2</IncentivadorCultural><Competencia>2026-02-01T00:00:00</Competencia><Servico><Valores><ValorServicos>1562.5</ValorServicos><ValorDeducoes>0</ValorDeducoes><ValorPis>10.16</ValorPis><ValorCofins>46.88</ValorCofins><ValorInss>0.0</ValorInss><ValorIr>0.0</ValorIr><ValorCsll>15.63</ValorCsll><ValorIss>31.25</ValorIss><OutrasRetencoes>0.0</OutrasRetencoes><BaseCalculo>1562.5</BaseCalculo><Aliquota>2.0</Aliquota><ValorLiquidoNfse>1458.58</ValorLiquidoNfse><DescontoCondicionado>0.0</DescontoCondicionado><DescontoIncondicionado>0.0</DescontoIncondicionado></Valores><IssRetido>1</IssRetido><ItemListaServico>140101</ItemListaServico><CodigoCnae/><Discriminacao>MANUTENCAO - REVISAO - RESTAURACAO Ordem de Servico 16554.|Vencimento(s): Parc:1/2 02/03/26 - Parc:2/2 23/03/26|VALOR APROX. TRIBUTOS: Federal R$ 122,66 (7,85%) Estadual R$ 281,25 (18,00%) Municipal R$ 31,25 (2,00%) FONTE: IBPT</Discriminacao><CodigoMunicipio>3506003</CodigoMunicipio><ExigibilidadeISS>1</ExigibilidadeISS></Servico><PrestadorServico><IdentificacaoPrestador><Cnpj>29726322000102</Cnpj><InscricaoMunicipal>573444</InscricaoMunicipal></IdentificacaoPrestador><RazaoSocial>EMPILHAX EQUIPAMENTOS LOCACOES COMERCIO DE PECAS E SERVICOS LTDA</RazaoSocial><NomeFantasia/><Endereco><Endereco>GONZAGA MACHADO, 1-53 - VILA ENGLER</Endereco><Numero>0001</Numero><Bairro>CEP 17047-090 - BAURU - SP</Bairro><CodigoMunicipio>3506003</CodigoMunicipio><Uf>SP</Uf><Cep>17047-090</Cep></Endereco><Contato><Telefone>14 3203-9181</Telefone></Contato></PrestadorServico><TomadorServico><IdentificacaoTomador><CpfCnpj><Cnpj>07962637000108</Cnpj></CpfCnpj></IdentificacaoTomador><RazaoSocial>EMPORIUM COMERCIO DE ACRILICOS EIRELI</RazaoSocial><Endereco><Endereco>AV MANOEL DUQUE</Endereco><Numero/><Bairro>JD GUADALAJARA</Bairro><CodigoMunicipio>3506003</CodigoMunicipio><Uf>SP</Uf><Cep>17030110</Cep></Endereco><Contato><Email>admin@emporiumacrilicos.com.br</Email></Contato></TomadorServico><OrgaoGerador><CodigoMunicipio>3506003</CodigoMunicipio><Uf>SP</Uf></OrgaoGerador></InfNfse></Nfse></CompNfse><CompNfse><Nfse><InfNfse id="27585"><Numero>27585</Numero><CodigoVerificacao>35060031200021422000143000000002758526020520321962</CodigoVerificacao><DataEmissao>2026-02-11T00:00:00</DataEmissao><IdentificacaoRps><Numero>36144</Numero><Serie>900</Serie><Tipo>1</Tipo><Status>1</Status></IdentificacaoRps><NaturezaOperacao>1</NaturezaOperacao><OptanteSimplesNacional>1</OptanteSimplesNacional><IncentivadorCultural>2</IncentivadorCultural><Competencia>2026-02-01T00:00:00</Competencia><Servico><Valores><ValorServicos>1223.0</ValorServicos><ValorDeducoes>0</ValorDeducoes><ValorPis>0.0</ValorPis><ValorCofins>0.0</ValorCofins><ValorInss>0.0</ValorInss><ValorIr>0.0</ValorIr><ValorCsll>0.0</ValorCsll><ValorIss>52.59</ValorIss><OutrasRetencoes>0.0</OutrasRetencoes><BaseCalculo>1223.0</BaseCalculo><Aliquota>4.3</Aliquota><ValorLiquidoNfse>1170.41</ValorLiquidoNfse><DescontoCondicionado>0.0</DescontoCondicionado><DescontoIncondicionado>0.0</DescontoIncondicionado></Valores><IssRetido>1</IssRetido><ItemListaServico>010401</ItemListaServico><CodigoCnae/><Discriminacao>MANUTENCAO E LICENCA DO SISTEMA</Discriminacao><CodigoMunicipio>3506003</CodigoMunicipio><ExigibilidadeISS>1</ExigibilidadeISS></Servico><PrestadorServico><IdentificacaoPrestador><Cnpj>00021422000143</Cnpj><InscricaoMunicipal>52080</InscricaoMunicipal></IdentificacaoPrestador><RazaoSocial>QUALITY SYSTEM INFORMATICA LTDA</RazaoSocial><NomeFantasia/><Endereco><Endereco>ALBERTO SEGALLA, 01-75 - JD. HENRIQUE</Endereco><Numero>0001</Numero><Bairro>CEP 17012-634 - BAURU - SP</Bairro><CodigoMunicipio>3506003</CodigoMunicipio><Uf>SP</Uf><Cep>17012-634</Cep></Endereco><Contato><Telefone>14 4009-1515</Telefone></Contato></PrestadorServico><TomadorServico><IdentificacaoTomador><CpfCnpj><Cnpj>07962637000108</Cnpj></CpfCnpj></IdentificacaoTomador><RazaoSocial>EMPORIUM COM DE ACRILICO LTDA EPP</RazaoSocial><Endereco><Endereco>AV AURELIANO CARDIA 6-60</Endereco><Numero/><Bairro>VILA CARDIA</Bairro><CodigoMunicipio>3506003</CodigoMunicipio><Uf>SP</Uf><Cep>17013411</Cep></Endereco><Contato><Email>admin@emporiumacrilicos.com.br</Email></Contato></TomadorServico><OrgaoGerador><CodigoMunicipio>3506003</CodigoMunicipio><Uf>SP</Uf></OrgaoGerador></InfNfse></Nfse></CompNfse><CompNfse><Nfse><InfNfse id="47208"><Numero>47208</Numero><CodigoVerificacao>35060031244456036000150000000004720826020521007377</CodigoVerificacao><DataEmissao>2026-02-13T00:00:00</DataEmissao><IdentificacaoRps><Numero>47077</Numero><Serie>00001</Serie><Tipo>1</Tipo><Status>1</Status></IdentificacaoRps><NaturezaOperacao>1</NaturezaOperacao><OptanteSimplesNacional>2</OptanteSimplesNacional><IncentivadorCultural>2</IncentivadorCultural><Competencia>2026-02-01T00:00:00</Competencia><Servico><Valores><ValorServicos>2373.14</ValorServicos><ValorDeducoes>0</ValorDeducoes><ValorPis>0.0</ValorPis><ValorCofins>0.0</ValorCofins><ValorInss>0.0</ValorInss><ValorIr>0.0</ValorIr><ValorCsll>0.0</ValorCsll><ValorIss>8.14</ValorIss><OutrasRetencoes>0.0</OutrasRetencoes><BaseCalculo>406.76</BaseCalculo><Aliquota>2.0</Aliquota><ValorLiquidoNfse>2373.14</ValorLiquidoNfse><DescontoCondicionado>0.0</DescontoCondicionado><DescontoIncondicionado>0.0</DescontoIncondicionado></Valores><IssRetido>2</IssRetido><ItemListaServico>042201</ItemListaServico><CodigoCnae/><Discriminacao>- Referente a fatura 4652811. Mensalidade Plano de Saúde:  R$ 2.235,04PRODUÇÃO DE COOPERADOS/PESSOA FÍSICA:  R$ 138,10</Discriminacao><CodigoMunicipio>3506003</CodigoMunicipio><ExigibilidadeISS>1</ExigibilidadeISS></Servico><PrestadorServico><IdentificacaoPrestador><Cnpj>44456036000150</Cnpj><InscricaoMunicipal>2340</InscricaoMunicipal></IdentificacaoPrestador><RazaoSocial>UNIMED DE BAURU COOPERATIVA DE TRABALHO MEDICO</RazaoSocial><NomeFantasia/><Endereco><Endereco>GUSTAVO MACIEL, 11-30 - CENTRO</Endereco><Numero>0001</Numero><Bairro>CEP 17015-320 - BAURU - SP</Bairro><CodigoMunicipio>3506003</CodigoMunicipio><Uf>SP</Uf><Cep>17015-320</Cep></Endereco><Contato><Telefone>1432353327</Telefone></Contato></PrestadorServico><TomadorServico><IdentificacaoTomador><CpfCnpj><Cnpj>07962637000108</Cnpj></CpfCnpj></IdentificacaoTomador><RazaoSocial>EMPORIUM COMERCIO DE ACRILICOS LTDA EPP</RazaoSocial><Endereco><Endereco>AV MANOEL DUQUE</Endereco><Numero/><Bairro>JARDIM GUADALAJARA</Bairro><CodigoMunicipio>3506003</CodigoMunicipio><Uf>SP</Uf><Cep>17030110</Cep></Endereco><Contato><Email>erika@emporiumacrilicos.com.br</Email></Contato></TomadorServico><OrgaoGerador><CodigoMunicipio>3506003</CodigoMunicipio><Uf>SP</Uf></OrgaoGerador></InfNfse></Nfse></CompNfse><CompNfse><Nfse><InfNfse id="51379"><Numero>51379</Numero><CodigoVerificacao>35060031253165106000535000000005137926020521174331</CodigoVerificacao><DataEmissao>2026-02-16T00:00:00</DataEmissao><IdentificacaoRps><Numero>51379</Numero><Serie>00002</Serie><Tipo>1</Tipo><Status>1</Status></IdentificacaoRps><NaturezaOperacao>1</NaturezaOperacao><OptanteSimplesNacional>2</OptanteSimplesNacional><IncentivadorCultural>2</IncentivadorCultural><Competencia>2026-02-01T00:00:00</Competencia><Servico><Valores><ValorServicos>440.0</ValorServicos><ValorDeducoes>0</ValorDeducoes><ValorPis>0.0</ValorPis><ValorCofins>0.0</ValorCofins><ValorInss>0.0</ValorInss><ValorIr>0.0</ValorIr><ValorCsll>0.0</ValorCsll><ValorIss>8.8</ValorIss><OutrasRetencoes>0.0</OutrasRetencoes><BaseCalculo>440.0</BaseCalculo><Aliquota>2.0</Aliquota><ValorLiquidoNfse>409.2</ValorLiquidoNfse><DescontoCondicionado>22.0</DescontoCondicionado><DescontoIncondicionado>0.0</DescontoIncondicionado></Valores><IssRetido>1</IssRetido><ItemListaServico>140101</ItemListaServico><CodigoCnae/><Discriminacao>TR TROCA OLEO E FILTROS Modelo:  VW 24-280 ADVANTECH CHASSI:953658242DR322064; Km : 543803 Placa : EKM4257  OS:00176429;  FABR/MOD: 2013/2013  COR: AZUL ESTRATOSFE  VEND. : LUCAS RAFAEL BASILIO   DEPTO : ASSIST.TECNICA - VOLKSWAGEN   VENC. : 18/03/2026 |  VENC. : 17/04/2026 |  VENC. : 18/05/2026 |GARANTIA PARA PECAS ORIGINAIS INSTALADAS NA OFICINA E DE 12 MESES SEM LIMITE DE QUILOMETRAGEM, CONF. CIRC. PA-110-11. NF. EMITIDA CONF. ARTIGO 36, PARAG. 4O. DO RICMS/00-SP. PECAS PARALELAS, GARANTIA DE 03 MESES. RET ISS     440,00 ALIQ  2,00 VR      8,80 VR LIQ     431,20                                                                                                                                                                                                                                                                                                                                                                                                                                                                                                                                                                      Valor Aproximado dos Tributos RS-47.02  Equivalente a 10.68%</Discriminacao><CodigoMunicipio>3506003</CodigoMunicipio><ExigibilidadeISS>1</ExigibilidadeISS></Servico><PrestadorServico><IdentificacaoPrestador><Cnpj>53165106000535</Cnpj><InscricaoMunicipal>63156</InscricaoMunicipal></IdentificacaoPrestador><RazaoSocial>MARKA VEICULOS LTDA</RazaoSocial><NomeFantasia/><Endereco><Endereco>JOAQUIM PELEGRINA LOPES, 03-50 - DISTR. INDUSTRIAL 3</Endereco><Numero>0001</Numero><Bairro>CEP 17064-851 - BAURU - SP</Bairro><CodigoMunicipio>3506003</CodigoMunicipio><Uf>SP</Uf><Cep>17064-851</Cep></Endereco><Contato><Telefone>14 3109-2500</Telefone></Contato></PrestadorServico><TomadorServico><IdentificacaoTomador><CpfCnpj><Cnpj>07962637000108</Cnpj></CpfCnpj></IdentificacaoTomador><RazaoSocial>EMPORIUM COMERCIO DE ACRILICOS LTDA</RazaoSocial><Endereco><Endereco>AVENIDA MANOEL DUQUE</Endereco><Numero/><Bairro>JARDIM GUADALAJARA</Bairro><CodigoMunicipio>3506003</CodigoMunicipio><Uf>SP</Uf><Cep>17013411</Cep></Endereco><Contato><Email>admin@emporiumacrilicos.com.br</Email></Contato></TomadorServico><OrgaoGerador><CodigoMunicipio>3506003</CodigoMunicipio><Uf>SP</Uf></OrgaoGerador></InfNfse></Nfse></CompNfse><CompNfse><Nfse><InfNfse id="41"><Numero>41</Numero><CodigoVerificacao>35060031257134540000185000000000004126020521538553</CodigoVerificacao><DataEmissao>2026-02-19T00:00:00</DataEmissao><IdentificacaoRps><Numero>41</Numero><Serie>49999</Serie><Tipo>1</Tipo><Status>1</Status></IdentificacaoRps><NaturezaOperacao>1</NaturezaOperacao><OptanteSimplesNacional>1</OptanteSimplesNacional><IncentivadorCultural>2</IncentivadorCultural><Competencia>2026-02-01T00:00:00</Competencia><Servico><Valores><ValorServicos>2000.0</ValorServicos><ValorDeducoes>0</ValorDeducoes><ValorPis>0.0</ValorPis><ValorCofins>0.0</ValorCofins><ValorInss>0.0</ValorInss><ValorIr>0.0</ValorIr><ValorCsll>0.0</ValorCsll><ValorIss>40.0</ValorIss><OutrasRetencoes>0.0</OutrasRetencoes><BaseCalculo>2000.0</BaseCalculo><Aliquota>2.0</Aliquota><ValorLiquidoNfse>1960.0</ValorLiquidoNfse><DescontoCondicionado>0.0</DescontoCondicionado><DescontoIncondicionado>0.0</DescontoIncondicionado></Valores><IssRetido>1</IssRetido><ItemListaServico>170601</ItemListaServico><CodigoCnae/><Discriminacao>Veiculação de anúncio (ed. 5) na revista Canal Bauru.</Discriminacao><CodigoMunicipio>3506003</CodigoMunicipio><ExigibilidadeISS>1</ExigibilidadeISS></Servico><PrestadorServico><IdentificacaoPrestador><Cnpj>57134540000185</Cnpj><InscricaoMunicipal>647853</InscricaoMunicipal></IdentificacaoPrestador><RazaoSocial>ZC EDITORA E COMUNICACAO LTDA</RazaoSocial><NomeFantasia/><Endereco><Endereco>AFFONSO JOSE AIELLO, 24-115 - VILA AVIACAO</Endereco><Numero>0001</Numero><Bairro>CEP 17018-520 - BAURU - SP</Bairro><CodigoMunicipio>3506003</CodigoMunicipio><Uf>SP</Uf><Cep>17018-520</Cep></Endereco><Contato><Telefone>(14)3227-0064</Telefone></Contato></PrestadorServico><TomadorServico><IdentificacaoTomador><CpfCnpj><Cnpj>07962637000108</Cnpj></CpfCnpj></IdentificacaoTomador><RazaoSocial>EMPORIUM COMERCIO DE ACRILICOS LTDA</RazaoSocial><Endereco><Endereco>AVENIDA MANOEL DUQUE 2-10</Endereco><Numero/><Bairro>JD. GUADALAJARA</Bairro><CodigoMunicipio>3506003</CodigoMunicipio><Uf>SP</Uf><Cep>17030-110</Cep></Endereco><Contato><Email>contato@jrassessoria.com.br</Email></Contato></TomadorServico><OrgaoGerador><CodigoMunicipio>3506003</CodigoMunicipio><Uf>SP</Uf></OrgaoGerador></InfNfse></Nfse></CompNfse><CompNfse><Nfse><InfNfse id="7756"><Numero>7756</Numero><CodigoVerificacao>35060031229726322000102000000000775626020522396707</CodigoVerificacao><DataEmissao>2026-02-24T00:00:00</DataEmissao><IdentificacaoRps><Numero>7756</Numero><Serie>1</Serie><Tipo>1</Tipo><Status>1</Status></IdentificacaoRps><NaturezaOperacao>1</NaturezaOperacao><OptanteSimplesNacional>1</OptanteSimplesNacional><IncentivadorCultural>2</IncentivadorCultural><Competencia>2026-02-01T00:00:00</Competencia><Servico><Valores><ValorServicos>4326.0</ValorServicos><ValorDeducoes>0</ValorDeducoes><ValorPis>28.12</ValorPis><ValorCofins>129.78</ValorCofins><ValorInss>0.0</ValorInss><ValorIr>0.0</ValorIr><ValorCsll>201.16</ValorCsll><ValorIss>86.52</ValorIss><OutrasRetencoes>0.0</OutrasRetencoes><BaseCalculo>4326.0</BaseCalculo><Aliquota>2.0</Aliquota><ValorLiquidoNfse>3880.42</ValorLiquidoNfse><DescontoCondicionado>0.0</DescontoCondicionado><DescontoIncondicionado>0.0</DescontoIncondicionado></Valores><IssRetido>1</IssRetido><ItemListaServico>140101</ItemListaServico><CodigoCnae/><Discriminacao>MANUTENCAO - REVISAO - RESTAURACAO Ordem de Servico 16348.|Vencimento(s): Parc:1/3 16/03/26 - Parc:2/3 06/04/26 - Parc:3/3 27/04/26|VALOR APROX. TRIBUTOS: Federal R$ 339,59 (7,85%) Estadual R$ 778,68 (18,00%) Municipal R$ 86,52 (2,00%) FONTE: IBPT</Discriminacao><CodigoMunicipio>3506003</CodigoMunicipio><ExigibilidadeISS>1</ExigibilidadeISS></Servico><PrestadorServico><IdentificacaoPrestador><Cnpj>29726322000102</Cnpj><InscricaoMunicipal>573444</InscricaoMunicipal></IdentificacaoPrestador><RazaoSocial>EMPILHAX EQUIPAMENTOS LOCACOES COMERCIO DE PECAS E SERVICOS LTDA</RazaoSocial><NomeFantasia/><Endereco><Endereco>GONZAGA MACHADO, 1-53 - VILA ENGLER</Endereco><Numero>0001</Numero><Bairro>CEP 17047-090 - BAURU - SP</Bairro><CodigoMunicipio>3506003</CodigoMunicipio><Uf>SP</Uf><Cep>17047-090</Cep></Endereco><Contato><Telefone>14 3203-9181</Telefone></Contato></PrestadorServico><TomadorServico><IdentificacaoTomador><CpfCnpj><Cnpj>07962637000108</Cnpj></CpfCnpj></IdentificacaoTomador><RazaoSocial>EMPORIUM COMERCIO DE ACRILICOS EIRELI</RazaoSocial><Endereco><Endereco>AV MANOEL DUQUE</Endereco><Numero/><Bairro>JD GUADALAJARA</Bairro><CodigoMunicipio>3506003</CodigoMunicipio><Uf>SP</Uf><Cep>17030110</Cep></Endereco><Contato><Email>admin@emporiumacrilicos.com.br</Email></Contato></TomadorServico><OrgaoGerador><CodigoMunicipio>3506003</CodigoMunicipio><Uf>SP</Uf></OrgaoGerador></InfNfse></Nfse></CompNfse><CompNfse><Nfse><InfNfse id="3173"><Numero>3173</Numero><CodigoVerificacao>35060031248840190000181000000000317326020522967136</CodigoVerificacao><DataEmissao>2026-02-27T00:00:00</DataEmissao><IdentificacaoRps><Numero>41472</Numero><Serie>1</Serie><Tipo>1</Tipo><Status>1</Status></IdentificacaoRps><NaturezaOperacao>1</NaturezaOperacao><OptanteSimplesNacional>1</OptanteSimplesNacional><IncentivadorCultural>2</IncentivadorCultural><Competencia>2026-02-01T00:00:00</Competencia><Servico><Valores><ValorServicos>2240.0</ValorServicos><ValorDeducoes>0</ValorDeducoes><ValorPis>0.0</ValorPis><ValorCofins>0.0</ValorCofins><ValorInss>0.0</ValorInss><ValorIr>0.0</ValorIr><ValorCsll>0.0</ValorCsll><ValorIss>63.84</ValorIss><OutrasRetencoes>0.0</OutrasRetencoes><BaseCalculo>2240.0</BaseCalculo><Aliquota>2.85</Aliquota><ValorLiquidoNfse>2176.16</ValorLiquidoNfse><DescontoCondicionado>0.0</DescontoCondicionado><DescontoIncondicionado>0.0</DescontoIncondicionado></Valores><IssRetido>1</IssRetido><ItemListaServico>170601</ItemListaServico><CodigoCnae/><Discriminacao>QT: 1,00 - CONSULTORIA EM MPI + 2 MAPS INDEXA + LOGO + FOTO 360 + ANUN GOLD - R$ 2.240,00 - Tot.R$ 2.240,00VENCIMENTO: 16/02/2026 - R$ 2.240,00 - FORMA PAGAMENTO: BOLETO BANCARIO</Discriminacao><CodigoMunicipio>3506003</CodigoMunicipio><ExigibilidadeISS>1</ExigibilidadeISS></Servico><PrestadorServico><IdentificacaoPrestador><Cnpj>48840190000181</Cnpj><InscricaoMunicipal>626954</InscricaoMunicipal></IdentificacaoPrestador><RazaoSocial>DISCOVERY MARKETING DIGITAL LTDA</RazaoSocial><NomeFantasia/><Endereco><Endereco>VIRGÍLIO MALTA, 17-76 - VILA MESQUITA</Endereco><Numero>0001</Numero><Bairro>CEP 17014-440 - BAURU - SP</Bairro><CodigoMunicipio>3506003</CodigoMunicipio><Uf>SP</Uf><Cep>17014-440</Cep></Endereco><Contato><Telefone>(14) 3104-1470</Telefone></Contato></PrestadorServico><TomadorServico><IdentificacaoTomador><CpfCnpj><Cnpj>07962637000108</Cnpj></CpfCnpj></IdentificacaoTomador><RazaoSocial>EMPORIUM COMERCIO DE ACRILICOS LTDA</RazaoSocial><Endereco><Endereco>AVENIDA MANOEL DUQUE</Endereco><Numero/><Bairro>JARDIM GUADALAJARA</Bairro><CodigoMunicipio>3506003</CodigoMunicipio><Uf>SP</Uf><Cep>17030110</Cep></Endereco><Contato><Email>ADMIN@EMPORIUMACRILICOS.COM.BR</Email></Contato></TomadorServico><OrgaoGerador><CodigoMunicipio>3506003</CodigoMunicipio><Uf>SP</Uf></OrgaoGerador></InfNfse></Nfse></CompNfse><CompNfse><Nfse><InfNfse id="3174"><Numero>3174</Numero><CodigoVerificacao>35060031248840190000181000000000317426020522967270</CodigoVerificacao><DataEmissao>2026-02-27T00:00:00</DataEmissao><IdentificacaoRps><Numero>41473</Numero><Serie>1</Serie><Tipo>1</Tipo><Status>1</Status></IdentificacaoRps><NaturezaOperacao>1</NaturezaOperacao><OptanteSimplesNacional>1</OptanteSimplesNacional><IncentivadorCultural>2</IncentivadorCultural><Competencia>2026-02-01T00:00:00</Competencia><Servico><Valores><ValorServicos>1210.0</ValorServicos><ValorDeducoes>0</ValorDeducoes><ValorPis>0.0</ValorPis><ValorCofins>0.0</ValorCofins><ValorInss>0.0</ValorInss><ValorIr>0.0</ValorIr><ValorCsll>0.0</ValorCsll><ValorIss>34.49</ValorIss><OutrasRetencoes>0.0</OutrasRetencoes><BaseCalculo>1210.0</BaseCalculo><Aliquota>2.85</Aliquota><ValorLiquidoNfse>1175.51</ValorLiquidoNfse><DescontoCondicionado>0.0</DescontoCondicionado><DescontoIncondicionado>0.0</DescontoIncondicionado></Valores><IssRetido>1</IssRetido><ItemListaServico>170601</ItemListaServico><CodigoCnae/><Discriminacao>QT: 1,00 - CONSULTORIA EM MPI + ANUN GOLD+ 15 CONTAS E-MAIL - R$ 1.210,00 - Tot.R$ 1.210,00VENCIMENTO: 07/02/2026 - R$ 1.210,00 - FORMA PAGAMENTO: BOLETO BANCARIO</Discriminacao><CodigoMunicipio>3506003</CodigoMunicipio><ExigibilidadeISS>1</ExigibilidadeISS></Servico><PrestadorServico><IdentificacaoPrestador><Cnpj>48840190000181</Cnpj><InscricaoMunicipal>626954</InscricaoMunicipal></IdentificacaoPrestador><RazaoSocial>DISCOVERY MARKETING DIGITAL LTDA</RazaoSocial><NomeFantasia/><Endereco><Endereco>VIRGÍLIO MALTA, 17-76 - VILA MESQUITA</Endereco><Numero>0001</Numero><Bairro>CEP 17014-440 - BAURU - SP</Bairro><CodigoMunicipio>3506003</CodigoMunicipio><Uf>SP</Uf><Cep>17014-440</Cep></Endereco><Contato><Telefone>(14) 3104-1470</Telefone></Contato></PrestadorServico><TomadorServico><IdentificacaoTomador><CpfCnpj><Cnpj>07962637000108</Cnpj></CpfCnpj></IdentificacaoTomador><RazaoSocial>EMPORIUM COMERCIO DE ACRILICOS LTDA</RazaoSocial><Endereco><Endereco>AVENIDA MANOEL DUQUE</Endereco><Numero/><Bairro>JARDIM GUADALAJARA</Bairro><CodigoMunicipio>3506003</CodigoMunicipio><Uf>SP</Uf><Cep>17030110</Cep></Endereco><Contato><Email>ADMIN@EMPORIUMACRILICOS.COM.BR</Email></Contato></TomadorServico><OrgaoGerador><CodigoMunicipio>3506003</CodigoMunicipio><Uf>SP</Uf></OrgaoGerador></InfNfse></Nfse></CompNfse></ListaNfse></ConsultarNfseResposta>